Sim_demo/cnt_ceil.v
//这是一个根据ceil信号改变进制的计数器
//这句在用Verilator静态检查时每个模块都要加的，如果有些模块有而有些模块没有则会报错
`timescale 1ns/1ns
//模块
module cnt_ceil(
  input        clk,
  input        en,
  input        rst_n,
  input  [3:0] ceil,
  output [3:0] cnt,
  output       co
);
  reg [3:0] cnt_reg;
  always@(posedge clk,negedge rst_n)
    begin
      if(!rst_n)
        cnt_reg <= 'b0;
      else
        if(en)
          if(cnt_reg >= ceil)
            cnt_reg <= 'b0;
          else
            cnt_reg <= cnt_reg + 1'b1;
    end
  assign cnt = cnt_reg;
  assign co  = en && (cnt_reg==ceil);
endmodule

Verilator Demo/Sim_Verilog_tb/cnt_ceil_tb.v
`timescale 1ns/1ns
module cnt_ceil_tb();
//输入信号
  reg        clk;
  reg        en;
  reg        rst_n;
  reg  [3:0] ceil;
//输出信号
  wire [3:0] cnt;
  wire       co;
//例化计数器
  cnt_ceil cnt_ceil_0(
    .clk   (clk),
    .en    (en),
    .rst_n (rst_n),
    .ceil  (ceil),
    .cnt   (cnt),
    .co    (co)
);
//初始化输入信号
  initial begin
    clk   = 1'b0;
    en    = 1'b0;
    rst_n = 1'b1;
    ceil  = 4'b1100;//12
  end
  initial begin//clk
    forever #1 clk = ~clk;
  end
  initial begin//en
    #1  en = 1'b1;
    #99 en = 1'b0;
  end
  initial begin//rst_n
    #10 rst_n = 1'b0;
    #1  rst_n = 1'b1;
  end
  initial begin//ceil
    #40 ceil = 4'b0110;//6
  end
  initial begin//finish
//重要的一句，在wrapper file的main函数里要能够识别到该完成语句作为结束运行的标志
    #110 $finish;
  end
endmodule

Sim_demo/obj_dir/cnt_ceil_wf.vcd
$version Generated by VerilatedVcd $end
$timescale 1s $end

 $scope module TOP $end
  $scope module cnt_ceil_tb $end
   $var wire  4 & ceil [3:0] $end
   $var wire  1 # clk $end
   $var wire  4 ' cnt [3:0] $end
   $var wire  1 ( co $end
   $var wire  1 $ en $end
   $var wire  1 % rst_n $end
   $scope module cnt_ceil_0 $end
    $var wire  4 & ceil [3:0] $end
    $var wire  1 # clk $end
    $var wire  4 ' cnt [3:0] $end
    $var wire  4 ' cnt_reg [3:0] $end
    $var wire  1 ( co $end
    $var wire  1 $ en $end
    $var wire  1 % rst_n $end
   $upscope $end
  $upscope $end
 $upscope $end
$enddefinitions $end


#0
0#
0$
1%
b1100 &
b0000 '
0(
#1
1#
1$
b0001 '
#2
0#
#3
1#
b0010 '
#4
0#
#5
1#
b0011 '
#6
0#
#7
1#
b0100 '
#8
0#
#9
1#
b0101 '
#10
0#
0%
b0000 '
#11
1#
1%
b0001 '
#12
0#
#13
1#
b0010 '
#14
0#
#15
1#
b0011 '
#16
0#
#17
1#
b0100 '
#18
0#
#19
1#
b0101 '
#20
0#
#21
1#
b0110 '
#22
0#
#23
1#
b0111 '
#24
0#
#25
1#
b1000 '
#26
0#
#27
1#
b1001 '
#28
0#
#29
1#
b1010 '
#30
0#
#31
1#
b1011 '
#32
0#
#33
1#
b1100 '
1(
#34
0#
#35
1#
b0000 '
0(
#36
0#
#37
1#
b0001 '
#38
0#
#39
1#
b0010 '
#40
0#
b0110 &
#41
1#
b0011 '
#42
0#
#43
1#
b0100 '
#44
0#
#45
1#
b0101 '
#46
0#
#47
1#
b0110 '
1(
#48
0#
#49
1#
b0000 '
0(
#50
0#
#51
1#
b0001 '
#52
0#
#53
1#
b0010 '
#54
0#
#55
1#
b0011 '
#56
0#
#57
1#
b0100 '
#58
0#
#59
1#
b0101 '
#60
0#
#61
1#
b0110 '
1(
#62
0#
#63
1#
b0000 '
0(
#64
0#
#65
1#
b0001 '
#66
0#
#67
1#
b0010 '
#68
0#
#69
1#
b0011 '
#70
0#
#71
1#
b0100 '
#72
0#
#73
1#
b0101 '
#74
0#
#75
1#
b0110 '
1(
#76
0#
#77
1#
b0000 '
0(
#78
0#
#79
1#
b0001 '
#80
0#
#81
1#
b0010 '
#82
0#
#83
1#
b0011 '
#84
0#
#85
1#
b0100 '
#86
0#
#87
1#
b0101 '
#88
0#
#89
1#
b0110 '
1(
#90
0#
#91
1#
b0000 '
0(
#92
0#
#93
1#
b0001 '
#94
0#
#95
1#
b0010 '
#96
0#
#97
1#
b0011 '
#98
0#
#99
1#
b0100 '
#100
0#
0$
